lab.cpython-39-darwin.so
lab/__init__.py
bindlab-0.0.3.dist-info/METADATA
bindlab-0.0.3.dist-info/WHEEL
bindlab-0.0.3.dist-info/top_level.txt
bindlab-0.0.3.dist-info/RECORD
