Metadata-Version: 2.1
Name: bindlab
Version: 0.0.3
Summary: A test project using pybind11 and CMake
Author: Marco Salvalaggio
Author-email: mar.salvalaggio@gmail.com
License: UNKNOWN
Platform: UNKNOWN
Requires-Python: >=3.7
Provides-Extra: test
Requires-Dist: pytest (>=6.0) ; extra == 'test'
